Metadata-Version: 1.1
Name: durable
Version: 0.1.4
Summary: Durable Rules Engine
Home-page: https://github.com/jruizgit/rules
Author: Jesus Ruiz
Author-email: jr3791@live.com
License: MIT
Keywords: rules_engine rete forward_chaining event_stream state_machine workflow consistency streaming_analytics
Platform: UNKNOWN
Classifier: Development Status :: 3 - Alpha
Classifier: Intended Audience :: Developers
Classifier: Topic :: Software Development :: Libraries
Classifier: License :: OSI Approved :: MIT License
Classifier: Programming Language :: Python :: 2.6
Classifier: Programming Language :: Python :: 2.7
